pyjanus/__init__.py
pyjanus/client.py
pyjanus/handle.py
pyjanus/plugins/__init__.py
pyjanus/plugins/videoroom.py
pyjanus/session.py
pyjanus/transaction.py
pyjanus/utils.py
pyjanus-0.1.0.dist-info/LICENSE
pyjanus-0.1.0.dist-info/WHEEL
pyjanus-0.1.0.dist-info/METADATA
pyjanus-0.1.0.dist-info/RECORD
